{"id": 4328, "uid": "0129b9e5-96fe-48a3-91f7-bd46316be737", "password": "2BFRpnMzC9", "first_name": "Levi", "last_name": "Hintz", "username": "levi.hintz", "email": "levi.hintz@email.com", "avatar": "https://robohash.org/explicabodelectusreiciendis.png?size=300x300&set=set1", "gender": "Male", "phone_number": "+54 906-935-0001 x524", "social_insurance_number": "671587517", "date_of_birth": "1978-08-26", "employment": {"title": "National Technology Facilitator", "key_skill": "Self-motivated"}, "address": {"city": "Stiedemannbury", "street_name": "Heathcote Fall", "street_address": "539 Brian Spurs", "zip_code": "33990", "state": "Vermont", "country": "United States", "coordinates": {"lat": -67.1282381851477, "lng": 52.836396987856915}}, "credit_card": {"cc_number": "4105-6577-7224-5182"}, "subscription": {"plan": "Gold", "status": "Blocked", "payment_method": "Credit card", "term": "Full subscription"}}